rawplot/__init__.py
rawplot/_version.py
rawplot/hv.py
rawplot/image.py
rawplot/imarith.py
rawplot/linearity.py
rawplot/master.py
rawplot/photodiode.py
rawplot/plan.py
rawplot/spectral.py
rawplot/ptc/__init__.py
rawplot/ptc/common.py
rawplot/ptc/noise_curves.py
rawplot/ptc/snr_curves.py
rawplot/ptc/table.py
rawplot/ptc/variance_curves.py
rawplot/resources/__init__.py
rawplot/resources/global.mplstyle
rawplot/util/__init__.py
rawplot/util/common.py
rawplot/util/analyzer/__init__.py
rawplot/util/analyzer/image.py
"rawplot/util/mpl/__init__,py"
rawplot/util/mpl/plot.py
rawplot-0.9.10.dist-info/LICENSE
rawplot-0.9.10.dist-info/METADATA
rawplot-0.9.10.dist-info/WHEEL
rawplot-0.9.10.dist-info/entry_points.txt
rawplot-0.9.10.dist-info/top_level.txt
rawplot-0.9.10.dist-info/RECORD
