Metadata-Version: 2.1
Name: rawplot
Version: 0.9.10
Summary: Plotting tools to analyze and characterize RGB imagers using Bayer raw images
Author-email: Rafael González <rafael08@ucm.es>, Jaime Zamorano <jzamoran@ucm.es>
License: MIT License
Project-URL: Homepage, https://github.com/guaix-ucm/rawplot
Project-URL: Repository, https://github.com/guaix-ucm/rawplot.git
Classifier: Programming Language :: Python :: 3.10
Classifier: Programming Language :: Python :: 3.11
Classifier: Programming Language :: Python :: 3.12
Classifier: Development Status :: 4 - Beta
Classifier: Environment :: Console
Classifier: Intended Audience :: Science/Research
Classifier: License :: OSI Approved :: GNU General Public License (GPL)
Classifier: Operating System :: OS Independent
Classifier: Topic :: Scientific/Engineering :: Astronomy
Classifier: Topic :: Scientific/Engineering :: Atmospheric Science
Requires-Python: >=3.10
License-File: LICENSE
Requires-Dist: matplotlib
Requires-Dist: PyQt5
Requires-Dist: scikit-learn
Requires-Dist: astropy
Requires-Dist: lica[lica,raw]
